persis/__init__.py
persis/persis.py
persis/data/data.txt
persis/data/df.pkl
persis/models/knn.pkl
persis-0.0.8.dist-info/AUTHORS.rst
persis-0.0.8.dist-info/LICENSE.txt
persis-0.0.8.dist-info/METADATA
persis-0.0.8.dist-info/WHEEL
persis-0.0.8.dist-info/top_level.txt
persis-0.0.8.dist-info/RECORD
