Metadata-Version: 2.1
Name: persis
Version: 0.0.8
Summary: A minimal example of packaging pickled data and models.
Home-page: https://github.com/marskar/persis
Author: Martin Skarzynski
Author-email: marskar@gmail.com
License: UNKNOWN
Platform: UNKNOWN
Classifier: Programming Language :: Python :: 3
Classifier: License :: OSI Approved :: MIT License
Classifier: Operating System :: OS Independent
